fastj/.DS_Store
fastj/__init__.py
fastj-0.1.0.dist-info/METADATA
fastj-0.1.0.dist-info/WHEEL
fastj-0.1.0.dist-info/RECORD
